LICENSE.txt
README.md
setup.py
ChromeController/__init__.py
ChromeController/__main__.py
ChromeController/chrome_context.py
ChromeController/cr_exceptions.py
ChromeController/exit_handler.py
ChromeController/filter_funcs.py
ChromeController/manager.py
ChromeController/manager_base.py
ChromeController/tab_pool.py
ChromeController/transport.py
ChromeController.egg-info/PKG-INFO
ChromeController.egg-info/SOURCES.txt
ChromeController.egg-info/dependency_links.txt
ChromeController.egg-info/requires.txt
ChromeController.egg-info/top_level.txt
ChromeController/Generator/Generated.py
ChromeController/Generator/__init__.py
ChromeController/Generator/gen.py
ChromeController/protocols/browser_protocol-r1.2.json
ChromeController/protocols/browser_protocol-r1.3-DEV.json
ChromeController/protocols/browser_protocol-r1.3.json
ChromeController/protocols/js_protocol-r1.2.json
ChromeController/protocols/js_protocol-r1.3-DEV.json
ChromeController/resources/__init__.py
ChromeController/resources/evasions.py
ChromeController/resources/js.py
ChromeController/resources/evasions/console_debug.js
ChromeController/resources/evasions/iframe_contentwindow.js
ChromeController/resources/evasions/media_codecs.js
ChromeController/resources/evasions/navigator_languages.js
ChromeController/resources/evasions/navigator_permissions.js
ChromeController/resources/evasions/navigator_plugins.js
ChromeController/resources/evasions/navigator_vendor.js
ChromeController/resources/evasions/navigator_webdriver.js
ChromeController/resources/evasions/webgl_vendor.js
ChromeController/resources/evasions/window_outerdimensions.js
tests/__init__.py
tests/test_header_overrides.py
tests/test_post.py
tests/test_redirects.py
tests/test_simple.py
tests/test_tab_pool.py
tests/test_xhr_get.py
tests/testing_server.py