Metadata-Version: 2.1
Name: ChromeController
Version: 0.3.32
Summary: Chrome Remote Debugger interface.
Home-page: https://github.com/fake-name/ChromeController
Author: Connor Wolf
Author-email: github@imaginaryindustries.com
License: UNKNOWN
Platform: UNKNOWN
Classifier: Programming Language :: Python :: 3
Classifier: Development Status :: 4 - Beta
Classifier: Intended Audience :: Developers
Classifier: Operating System :: POSIX :: Linux
License-File: LICENSE.txt
